{
    "keep": {
        "days": true,
        "amount": 1
    },
    "auditLog": "C:\\Users\\kawsa\\Desktop\\khairul-dewan\\winston\\success\\.ff32971c00a246f7554958c2f1a0a62f4594ddc8-audit.json",
    "files": [
        {
            "date": 1775705754978,
            "name": "C:\\Users\\kawsa\\Desktop\\khairul-dewan\\winston\\success\\09-04-2026-09-success.log",
            "hash": "743440a7679017231f870891ea269557460af002cbbe06fbd46a75941a6acc95"
        },
        {
            "date": 1775709688774,
            "name": "C:\\Users\\kawsa\\Desktop\\khairul-dewan\\winston\\success\\09-04-2026-10-success.log",
            "hash": "ab45906b83f1fcfea874f5f168e0397a0cdc65a19aba286e307eb63f6c95e01b"
        },
        {
            "date": 1775731299943,
            "name": "C:\\Users\\kawsa\\Desktop\\khairul-dewan\\winston\\success\\09-04-2026-16-success.log",
            "hash": "bd0d970c6bddef44b0007e455f4b16f6d5ea668036c3baefbf8e38f17a1af851"
        },
        {
            "date": 1775732908545,
            "name": "C:\\Users\\kawsa\\Desktop\\khairul-dewan\\winston\\success\\09-04-2026-17-success.log",
            "hash": "a039662bac5c2b6a6f061640f5d32d6c8c8e7c58489967216d0667e4f9e85289"
        }
    ],
    "hashType": "sha256"
}